occasionally/__init__.py
occasionally/log.py
occasionally/priority_queue.py
occasionally/scheduler.py
occasionally/task.py
occasionally/time_helpers.py
occasionally-0.0.2.dist-info/LICENSE
occasionally-0.0.2.dist-info/METADATA
occasionally-0.0.2.dist-info/WHEEL
occasionally-0.0.2.dist-info/top_level.txt
occasionally-0.0.2.dist-info/zip-safe
occasionally-0.0.2.dist-info/RECORD
