Metadata-Version: 2.1
Name: occasionally
Version: 0.0.2
Summary: UNKNOWN
Home-page: https://github.com/dleonard203/occasionally
Author: Dave Leonard
License: MIT
Keywords: task scheduler
Platform: UNKNOWN
Classifier: License :: OSI Approved :: MIT License
Classifier: Programming Language :: Python
Classifier: Programming Language :: Python :: 2.7
Classifier: Intended Audience :: Developers
